examples/__init__.py
examples/sync_reports.py
gsuite_exporter/__init__.py
gsuite_exporter/auth.py
gsuite_exporter/cli.py
gsuite_exporter/collectors/__init__.py
gsuite_exporter/collectors/reports.py
gsuite_exporter/exporters/__init__.py
gsuite_exporter/exporters/base.py
gsuite_exporter/exporters/stackdriver_exporter.py
gsuite_exporter-0.0.4.dist-info/METADATA
gsuite_exporter-0.0.4.dist-info/WHEEL
gsuite_exporter-0.0.4.dist-info/entry_points.txt
gsuite_exporter-0.0.4.dist-info/top_level.txt
gsuite_exporter-0.0.4.dist-info/RECORD
