Metadata-Version: 2.1
Name: gsuite-exporter
Version: 0.0.4
Summary: GSuite Admin API Exporter
Home-page: UNKNOWN
Author: Google Inc.
Author-email: ocervello@google.com
License: UNKNOWN
Keywords: gsuite exporter stackdriver
Platform: UNKNOWN
Classifier: Development Status :: 3 - Alpha
Classifier: Intended Audience :: Developers
Classifier: Topic :: Software Development :: Build Tools
Classifier: License :: OSI Approved :: MIT License
Classifier: Programming Language :: Python :: 2
Classifier: Programming Language :: Python :: 2.7
Classifier: Programming Language :: Python :: 3
Classifier: Programming Language :: Python :: 3.4
Classifier: Programming Language :: Python :: 3.5
Classifier: Programming Language :: Python :: 3.6
Requires-Python: >=2.7
Requires-Dist: google-api-python-client
Requires-Dist: python-dateutil
Requires-Dist: requests
